cloey/__init__.py
cloey/framework.py
cloey-0.1.3.dist-info/LICENSE
cloey-0.1.3.dist-info/METADATA
cloey-0.1.3.dist-info/WHEEL
cloey-0.1.3.dist-info/top_level.txt
cloey-0.1.3.dist-info/RECORD
